LICENSE
MANIFEST.in
README.rst
setup.py
django_stringfield.egg-info/PKG-INFO
django_stringfield.egg-info/SOURCES.txt
django_stringfield.egg-info/dependency_links.txt
django_stringfield.egg-info/not-zip-safe
django_stringfield.egg-info/top_level.txt
stringfield/__init__.py
stringfield/base.py
stringfield/models.py
stringfield/tests.py