Metadata-Version: 1.0
Name: django-stringfield
Version: 0.3.0
Summary: Better string field for Django.
Home-page: https://github.com/aino/django-stringfield
Author: Mikko Hellsing
Author-email: mikko@aino.se
License: BSD
Platform: UNKNOWN
Classifier: Development Status :: 5 - Production/Stable
Classifier: Environment :: Web Environment
Classifier: Intended Audience :: Developers
Classifier: License :: OSI Approved :: BSD License
Classifier: Operating System :: OS Independent
Classifier: Programming Language :: Python
Classifier: Topic :: Internet :: WWW/HTTP :: Dynamic Content
Classifier: Framework :: Django
